django_prbac/__init__.py
django_prbac/admin.py
django_prbac/arbitrary.py
django_prbac/csv.py
django_prbac/decorators.py
django_prbac/exceptions.py
django_prbac/fields.py
django_prbac/forms.py
django_prbac/models.py
django_prbac/urls.py
django_prbac/utils.py
django_prbac/migrations/0001_initial.py
django_prbac/migrations/__init__.py
django_prbac-1.1.2.dist-info/licenses/LICENSE
django_prbac-1.1.2.dist-info/METADATA
django_prbac-1.1.2.dist-info/WHEEL
django_prbac-1.1.2.dist-info/top_level.txt
django_prbac-1.1.2.dist-info/RECORD
