Metadata-Version: 2.4
Name: django-prbac
Version: 1.1.2
Summary: Parameterized Role-Based Access Control for Django
Author-email: Dimagi <dev@dimagi.com>
Project-URL: Homepage, http://github.com/dimagi/django-prbac
Project-URL: Repository, https://github.com/dimagi/django-prbac
Classifier: Development Status :: 3 - Alpha
Classifier: Environment :: Web Environment
Classifier: Framework :: Django
Classifier: Framework :: Django :: 4
Classifier: Framework :: Django :: 4.2
Classifier: Framework :: Django :: 5
Classifier: Framework :: Django :: 5.1
Classifier: Framework :: Django :: 5.2
Classifier: Intended Audience :: Developers
Classifier: Operating System :: OS Independent
Classifier: Programming Language :: Python
Classifier: Programming Language :: Python :: 3
Classifier: Programming Language :: Python :: 3.9
Classifier: Programming Language :: Python :: 3.10
Classifier: Programming Language :: Python :: 3.11
Classifier: Programming Language :: Python :: 3.12
Classifier: Programming Language :: Python :: 3.13
Classifier: Topic :: Software Development :: Libraries :: Python Modules
Requires-Python: >=3.9
License-File: LICENSE
Requires-Dist: django
Requires-Dist: jsonfield
Requires-Dist: simplejson
Dynamic: license-file
